pyslice/__init__.py
pyslice/pyslice_lib/__init__.py
pyslice/pyslice_lib/PySPG/Agrizer.py
pyslice/pyslice_lib/PySPG/Executor.py
pyslice/pyslice_lib/PySPG/Load.py
pyslice/pyslice_lib/PySPG/MatrixPlotter.py
pyslice/pyslice_lib/PySPG/MeanCalculation.py
pyslice/pyslice_lib/PySPG/MultiAgrizer.py
pyslice/pyslice_lib/PySPG/ParamIterators.py
pyslice/pyslice_lib/PySPG/ParamParser.py
pyslice/pyslice_lib/PySPG/PyGrace.py
pyslice/pyslice_lib/PySPG/TeXParser.py
pyslice/pyslice_lib/PySPG/__init__.py
pyslice/pyslice_lib/PySPG/changelog
pyslice/pyslice_lib/PySPG/histogram.py
pyslice/pyslice_lib/PySPG/todo
pyslice/pyslice_lib/PySPG/scripts/mean.py
pyslice/pyslice_lib/PySPG/scripts/plot.py
pyslice/pyslice_lib/PySPG/scripts/plotcols.py
pyslice/pyslice_lib/PySPG/scripts/plotconf.py
pyslice/pyslice_lib/PySPG/scripts/plotdy.py
pyslice/pyslice_lib/PySPG/scripts/plotdyconf.py
pyslice/pyslice_lib/PySPG/scripts/plotfile.py
pyslice/pyslice_lib/PySPG/scripts/plothist.py
pyslice/pyslice_lib/PySPG/scripts/plotmulticols.py
pyslice/pyslice_lib/PySPG/scripts/plotmultifile.py
pyslice/pyslice_lib/PySPG/scripts/plotmultihist.py
pyslice/pyslice_lib/PySPG/scripts/varying.py
pyslice-6.0.3.dist-info/LICENSE.txt
pyslice-6.0.3.dist-info/METADATA
pyslice-6.0.3.dist-info/WHEEL
pyslice-6.0.3.dist-info/entry_points.txt
pyslice-6.0.3.dist-info/top_level.txt
pyslice-6.0.3.dist-info/RECORD
